lilliepy_import/__init__.py
lilliepy_import/main.py
lilliepy_import-0.1.dist-info/METADATA
lilliepy_import-0.1.dist-info/WHEEL
lilliepy_import-0.1.dist-info/top_level.txt
lilliepy_import-0.1.dist-info/RECORD
