Metadata-Version: 2.1
Name: lilliepy-import
Version: 0.1
Summary: dynamic importer for LilliePy framework
Home-page: https://github.com/websitedeb/lilliepy-import
Author: Sarthak Ghoshal
Author-email: sarthak22.ghoshal@gmail.com
License: MIT
Keywords: lilliepy,lilliepy-importer,reactpy
Classifier: Programming Language :: Python :: 3
Classifier: License :: OSI Approved :: MIT License
Classifier: Operating System :: OS Independent
Requires-Python: >=3.6
